spluscalib/__init__.py
spluscalib/dust_laws.py
spluscalib/pipeline.py
spluscalib/pipeline_backup.py
spluscalib/quality_check.py
spluscalib/quality_check_PSF.py
spluscalib/quality_check_PSFbackup.py
spluscalib/sed_fitting.py
spluscalib/utils.py
spluscalib/additionalsteps/__init__.py
spluscalib/additionalsteps/combine_calibration_catalogs.py
spluscalib/additionalsteps/compute_XY_maps.py
spluscalib/additionalsteps/compute_XY_maps_gaiaXPSP.py
spluscalib/additionalsteps/compute_XY_maps_v2.py
spluscalib/additionalsteps/concat_zp_catalogs.py
spluscalib/additionalsteps/fit_inst_offsets.py
spluscalib/additionalsteps/fit_zp_offsets.py
spluscalib/steps/__init__.py
spluscalib/steps/calibration_catalog.py
spluscalib/steps/calibration_diagnostic.py
spluscalib/steps/calibration_external.py
spluscalib/steps/calibration_finalzp.py
spluscalib/steps/calibration_gaiaXPSP.py
spluscalib/steps/calibration_gaiascale.py
spluscalib/steps/calibration_internal.py
spluscalib/steps/calibration_stloc.py
spluscalib/steps/check_xy_zp.py
spluscalib/steps/copy_images.py
spluscalib/steps/correction_aper.py
spluscalib/steps/correction_xy.py
spluscalib/steps/crossmatch.py
spluscalib/steps/final_checks.py
spluscalib/steps/photometry_ID.py
spluscalib/steps/photometry_aperimages.py
spluscalib/steps/photometry_dual.py
spluscalib/steps/photometry_master.py
spluscalib/steps/photometry_psf.py
spluscalib/steps/photometry_res.py
spluscalib/steps/photometry_single.py
spluscalib/steps/plot_mosaic_calib.py
spluscalib/steps/plot_mosaic_calib_v2.py
spluscalib/steps/plot_mosaic_calib_v3.py
spluscalib/steps/resources/SExsplus.param
spluscalib/steps/resources/SExsplus.sex
spluscalib/steps/resources/__init__.py
spluscalib/steps/resources/default_config.conf
spluscalib/steps/resources/dophot_paramdefault
spluscalib/steps/resources/swarpsplus.swarp
spluscalib/vacs/__init__.py
stellarlibrary/__init__.py
stellarlibrary/dust_laws.py
stellarlibrary/generate_models_photometry.py
spluscalib-0.5.2.dist-info/LICENSE
spluscalib-0.5.2.dist-info/METADATA
spluscalib-0.5.2.dist-info/WHEEL
spluscalib-0.5.2.dist-info/top_level.txt
spluscalib-0.5.2.dist-info/RECORD
