Metadata-Version: 2.1
Name: spluscalib
Version: 0.5.2
Summary: S-PLUS calibration pipeline
Home-page: https://github.com/felipefer42/spluscalib
Author: Felipe Almeida Fernandes
Author-email: felipefer42@gmail.com
License: UNKNOWN
Platform: UNKNOWN
Requires-Python: >3.7.0
License-File: LICENSE
Requires-Dist: astropy
Requires-Dist: astroquery
Requires-Dist: sfdmap
Requires-Dist: numpy
Requires-Dist: pandas
Requires-Dist: scipy
Requires-Dist: sklearn
Requires-Dist: matplotlib
Requires-Dist: shapely
Requires-Dist: Pillow
Requires-Dist: termcolor
Requires-Dist: cmasher
Requires-Dist: cartopy
Requires-Dist: gaiaxpy
